{
    "Print to console": {
        "prefix": "clg",
        "body": [
            "console.log($1);",
            "$2"
        ],
        "description": "Log output to console"
    },
    "for statement": {
        "prefix": "for",
        "body": [
            "for (var i = 0; i < $1; i++) {",
            "   $2",
            "}"
        ],
        "description": "my for snippet"
    },
    "then statement": {
        "prefix": "then",
        "body": [
            "then($1 => {",
            "   $2",
            "})"
        ],
        "description": "my then snippet"
    },
    "catch statement": {
        "prefix": "cat",
        "body": [
            "catch(err => {",
            "   $1",
            "})"
        ]
    }
}